econ_llm/agent.py
econ_llm/experiment.py
econ_llm/main.py
econ_llm/parser.py
econ_llm/prompt_strs.py
econ_llm/prompts.py
econ_llm-3.0.1.dist-info/licenses/LICENSE
econ_llm-3.0.1.dist-info/METADATA
econ_llm-3.0.1.dist-info/WHEEL
econ_llm-3.0.1.dist-info/entry_points.txt
econ_llm-3.0.1.dist-info/top_level.txt
econ_llm-3.0.1.dist-info/RECORD
