Metadata-Version: 2.4
Name: econ-llm
Version: 3.0.1
Summary: LLM Agents for Game Theory Experiments
Author-email: Jawand Singh <jawandsingh@gmail.com>
License: GNU GENERAL PUBLIC LICENSE
Project-URL: repository, https://github.com/JawandS/gt-agents/tree/main/econ-llm
Keywords: game theory,LLM,agents,experiments
Classifier: License :: OSI Approved :: GNU General Public License v3 (GPLv3)
Classifier: Programming Language :: Python :: 3
Requires-Python: >=3.9
License-File: LICENSE
Requires-Dist: openai==1.61.0
Requires-Dist: matplotlib==3.10.0
Requires-Dist: selenium==4.28.1
Requires-Dist: chromedriver-autoinstaller==0.6.4
Requires-Dist: pandas==2.2.3
Requires-Dist: tabulate==0.9.0
Requires-Dist: setuptools==75.8.0
Dynamic: license-file
